ryper/__init__.py
ryper/my_module.py
test/__init__.py
test/unit/__init__.py
test/unit/conftest.py
test/unit/test_my_module.py
ryper-0.0.0.dist-info/LICENSE
ryper-0.0.0.dist-info/METADATA
ryper-0.0.0.dist-info/WHEEL
ryper-0.0.0.dist-info/top_level.txt
ryper-0.0.0.dist-info/RECORD
